ducktype_mypy_plugin/__init__.py
ducktype_mypy_plugin/plugin.py
ducktype_mypy_plugin/py.typed
pyvista_mypy_plugin/__init__.py
pyvista_mypy_plugin/mypy_plugin.py
pyvista_mypy_plugin/py.typed
ducktype_mypy_plugin-0.2.dev1.dist-info/LICENSE
ducktype_mypy_plugin-0.2.dev1.dist-info/METADATA
ducktype_mypy_plugin-0.2.dev1.dist-info/WHEEL
ducktype_mypy_plugin-0.2.dev1.dist-info/top_level.txt
ducktype_mypy_plugin-0.2.dev1.dist-info/RECORD
