Metadata-Version: 2.1
Name: ducktype-mypy-plugin
Version: 0.2.dev1
Summary: Duck-typing plugin for mypy.
License: MIT
Project-URL: Homepage, https://github.com/pyvista/ducktype-mypy-plugin
Keywords: mypy,typing
Requires-Python: >=3.9
License-File: LICENSE
Requires-Dist: mypy
Provides-Extra: dev
Requires-Dist: pytest; extra == "dev"
Requires-Dist: pytest-mypy-plugins; extra == "dev"
Requires-Dist: pre-commit; extra == "dev"
